<?xml version="1.0" encoding="UTF-8"?>
<objects serializationModel="Studio.02.03.00">
	<object class="AudioFile" id="{9a577c2a-4a97-447a-8278-71c7364cde9c}">
		<property name="assetPath">
			<value>Fight, Bodyfall, Grass, Moderate Long Bodyfall 01 SND120859.wav</value>
		</property>
		<property name="frequencyInKHz">
			<value>96</value>
		</property>
		<property name="channelCount">
			<value>2</value>
		</property>
		<property name="length">
			<value>1.4637291666666667</value>
		</property>
		<relationship name="masterAssetFolder">
			<destination>{c62893bc-ff35-4987-972f-338739a0a3a6}</destination>
		</relationship>
	</object>
</objects>
